{"/*":["X-Frame-Options: DENY","X-XSS-Protection: 1; mode=block","X-Content-Type-Options: nosniff","Referrer-Policy: same-origin"],"/commons-c04d24b289df3efc440d.js":["Cache-Control: public, max-age=31536000, immutable"],"/component---src-pages-404-js-99f86495afad940a713e.js":["Cache-Control: public, max-age=31536000, immutable"],"/styles.6e4a75eff35094909de5.css":["Cache-Control: public, max-age=31536000, immutable"],"/cd082157ac999ace7b6ef0aba5c3818f2d68832b-7fddd33924e871593255.js":["Cache-Control: public, max-age=31536000, immutable"],"/component---src-pages-index-js-b3401ff644fc436bb23e.js":["Cache-Control: public, max-age=31536000, immutable"],"/component---src-pages-product-card-js-cfe175ebf656807c1aa6.js":["Cache-Control: public, max-age=31536000, immutable"],"/component---src-pages-using-typescript-tsx-192e6058c709fbfe299f.js":["Cache-Control: public, max-age=31536000, immutable"],"/webpack-runtime-a3f249b8dd01a6115604.js":["Cache-Control: public, max-age=31536000, immutable"],"/framework-7ed2d1b310e30335962d.js":["Cache-Control: public, max-age=31536000, immutable"],"/app-8df6d1293e42d5f129f4.js":["Cache-Control: public, max-age=31536000, immutable"],"/static/*":["Cache-Control: public, max-age=31536000, immutable"],"/sw.js":["Cache-Control: public, max-age=0, must-revalidate"],"/ru/404/":["Link: </webpack-runtime-a3f249b8dd01a6115604.js>; rel=preload; as=script; nopush","Link: </framework-7ed2d1b310e30335962d.js>; rel=preload; as=script; nopush","Link: </app-8df6d1293e42d5f129f4.js>; rel=preload; as=script; nopush","Link: </commons-c04d24b289df3efc440d.js>; rel=preload; as=script; nopush","Link: </component---src-pages-404-js-99f86495afad940a713e.js>; rel=preload; as=script; nopush","Link: </page-data/app-data.json>; rel=preload; as=fetch; crossorigin; nopush","Link: </page-data/ru/404/page-data.json>; rel=preload; as=fetch; crossorigin; nopush"],"/en/404/":["Link: </webpack-runtime-a3f249b8dd01a6115604.js>; rel=preload; as=script; nopush","Link: </framework-7ed2d1b310e30335962d.js>; rel=preload; as=script; nopush","Link: </app-8df6d1293e42d5f129f4.js>; rel=preload; as=script; nopush","Link: </commons-c04d24b289df3efc440d.js>; rel=preload; as=script; nopush","Link: </component---src-pages-404-js-99f86495afad940a713e.js>; rel=preload; as=script; nopush","Link: </page-data/app-data.json>; rel=preload; as=fetch; crossorigin; nopush","Link: </page-data/en/404/page-data.json>; rel=preload; as=fetch; crossorigin; nopush"],"/ru/":["Link: </webpack-runtime-a3f249b8dd01a6115604.js>; rel=preload; as=script; nopush","Link: </framework-7ed2d1b310e30335962d.js>; rel=preload; as=script; nopush","Link: </app-8df6d1293e42d5f129f4.js>; rel=preload; as=script; nopush","Link: </commons-c04d24b289df3efc440d.js>; rel=preload; as=script; nopush","Link: </cd082157ac999ace7b6ef0aba5c3818f2d68832b-7fddd33924e871593255.js>; rel=preload; as=script; nopush","Link: </component---src-pages-index-js-b3401ff644fc436bb23e.js>; rel=preload; as=script; nopush","Link: </page-data/app-data.json>; rel=preload; as=fetch; crossorigin; nopush","Link: </page-data/ru/page-data.json>; rel=preload; as=fetch; crossorigin; nopush"],"/en/":["Link: </webpack-runtime-a3f249b8dd01a6115604.js>; rel=preload; as=script; nopush","Link: </framework-7ed2d1b310e30335962d.js>; rel=preload; as=script; nopush","Link: </app-8df6d1293e42d5f129f4.js>; rel=preload; as=script; nopush","Link: </commons-c04d24b289df3efc440d.js>; rel=preload; as=script; nopush","Link: </cd082157ac999ace7b6ef0aba5c3818f2d68832b-7fddd33924e871593255.js>; rel=preload; as=script; nopush","Link: </component---src-pages-index-js-b3401ff644fc436bb23e.js>; rel=preload; as=script; nopush","Link: </page-data/app-data.json>; rel=preload; as=fetch; crossorigin; nopush","Link: </page-data/en/page-data.json>; rel=preload; as=fetch; crossorigin; nopush"],"/ru/product-card/":["Link: </webpack-runtime-a3f249b8dd01a6115604.js>; rel=preload; as=script; nopush","Link: </framework-7ed2d1b310e30335962d.js>; rel=preload; as=script; nopush","Link: </app-8df6d1293e42d5f129f4.js>; rel=preload; as=script; nopush","Link: </commons-c04d24b289df3efc440d.js>; rel=preload; as=script; nopush","Link: </cd082157ac999ace7b6ef0aba5c3818f2d68832b-7fddd33924e871593255.js>; rel=preload; as=script; nopush","Link: </component---src-pages-product-card-js-cfe175ebf656807c1aa6.js>; rel=preload; as=script; nopush","Link: </page-data/app-data.json>; rel=preload; as=fetch; crossorigin; nopush","Link: </page-data/ru/product-card/page-data.json>; rel=preload; as=fetch; crossorigin; nopush"],"/en/product-card/":["Link: </webpack-runtime-a3f249b8dd01a6115604.js>; rel=preload; as=script; nopush","Link: </framework-7ed2d1b310e30335962d.js>; rel=preload; as=script; nopush","Link: </app-8df6d1293e42d5f129f4.js>; rel=preload; as=script; nopush","Link: </commons-c04d24b289df3efc440d.js>; rel=preload; as=script; nopush","Link: </cd082157ac999ace7b6ef0aba5c3818f2d68832b-7fddd33924e871593255.js>; rel=preload; as=script; nopush","Link: </component---src-pages-product-card-js-cfe175ebf656807c1aa6.js>; rel=preload; as=script; nopush","Link: </page-data/app-data.json>; rel=preload; as=fetch; crossorigin; nopush","Link: </page-data/en/product-card/page-data.json>; rel=preload; as=fetch; crossorigin; nopush"],"/ru/using-typescript/":["Link: </webpack-runtime-a3f249b8dd01a6115604.js>; rel=preload; as=script; nopush","Link: </framework-7ed2d1b310e30335962d.js>; rel=preload; as=script; nopush","Link: </app-8df6d1293e42d5f129f4.js>; rel=preload; as=script; nopush","Link: </commons-c04d24b289df3efc440d.js>; rel=preload; as=script; nopush","Link: </component---src-pages-using-typescript-tsx-192e6058c709fbfe299f.js>; rel=preload; as=script; nopush","Link: </page-data/app-data.json>; rel=preload; as=fetch; crossorigin; nopush","Link: </page-data/ru/using-typescript/page-data.json>; rel=preload; as=fetch; crossorigin; nopush"],"/en/using-typescript/":["Link: </webpack-runtime-a3f249b8dd01a6115604.js>; rel=preload; as=script; nopush","Link: </framework-7ed2d1b310e30335962d.js>; rel=preload; as=script; nopush","Link: </app-8df6d1293e42d5f129f4.js>; rel=preload; as=script; nopush","Link: </commons-c04d24b289df3efc440d.js>; rel=preload; as=script; nopush","Link: </component---src-pages-using-typescript-tsx-192e6058c709fbfe299f.js>; rel=preload; as=script; nopush","Link: </page-data/app-data.json>; rel=preload; as=fetch; crossorigin; nopush","Link: </page-data/en/using-typescript/page-data.json>; rel=preload; as=fetch; crossorigin; nopush"],"/404/":["Link: </webpack-runtime-a3f249b8dd01a6115604.js>; rel=preload; as=script; nopush","Link: </framework-7ed2d1b310e30335962d.js>; rel=preload; as=script; nopush","Link: </app-8df6d1293e42d5f129f4.js>; rel=preload; as=script; nopush","Link: </commons-c04d24b289df3efc440d.js>; rel=preload; as=script; nopush","Link: </component---src-pages-404-js-99f86495afad940a713e.js>; rel=preload; as=script; nopush","Link: </page-data/app-data.json>; rel=preload; as=fetch; crossorigin; nopush","Link: </page-data/404/page-data.json>; rel=preload; as=fetch; crossorigin; nopush"],"/404.html":["Link: </webpack-runtime-a3f249b8dd01a6115604.js>; rel=preload; as=script; nopush","Link: </framework-7ed2d1b310e30335962d.js>; rel=preload; as=script; nopush","Link: </app-8df6d1293e42d5f129f4.js>; rel=preload; as=script; nopush","Link: </commons-c04d24b289df3efc440d.js>; rel=preload; as=script; nopush","Link: </component---src-pages-404-js-99f86495afad940a713e.js>; rel=preload; as=script; nopush","Link: </page-data/app-data.json>; rel=preload; as=fetch; crossorigin; nopush","Link: </page-data/404.html/page-data.json>; rel=preload; as=fetch; crossorigin; nopush"],"/":["Link: </webpack-runtime-a3f249b8dd01a6115604.js>; rel=preload; as=script; nopush","Link: </framework-7ed2d1b310e30335962d.js>; rel=preload; as=script; nopush","Link: </app-8df6d1293e42d5f129f4.js>; rel=preload; as=script; nopush","Link: </commons-c04d24b289df3efc440d.js>; rel=preload; as=script; nopush","Link: </cd082157ac999ace7b6ef0aba5c3818f2d68832b-7fddd33924e871593255.js>; rel=preload; as=script; nopush","Link: </component---src-pages-index-js-b3401ff644fc436bb23e.js>; rel=preload; as=script; nopush","Link: </page-data/app-data.json>; rel=preload; as=fetch; crossorigin; nopush","Link: </page-data/index/page-data.json>; rel=preload; as=fetch; crossorigin; nopush"],"/product-card/":["Link: </webpack-runtime-a3f249b8dd01a6115604.js>; rel=preload; as=script; nopush","Link: </framework-7ed2d1b310e30335962d.js>; rel=preload; as=script; nopush","Link: </app-8df6d1293e42d5f129f4.js>; rel=preload; as=script; nopush","Link: </commons-c04d24b289df3efc440d.js>; rel=preload; as=script; nopush","Link: </cd082157ac999ace7b6ef0aba5c3818f2d68832b-7fddd33924e871593255.js>; rel=preload; as=script; nopush","Link: </component---src-pages-product-card-js-cfe175ebf656807c1aa6.js>; rel=preload; as=script; nopush","Link: </page-data/app-data.json>; rel=preload; as=fetch; crossorigin; nopush","Link: </page-data/product-card/page-data.json>; rel=preload; as=fetch; crossorigin; nopush"],"/using-typescript/":["Link: </webpack-runtime-a3f249b8dd01a6115604.js>; rel=preload; as=script; nopush","Link: </framework-7ed2d1b310e30335962d.js>; rel=preload; as=script; nopush","Link: </app-8df6d1293e42d5f129f4.js>; rel=preload; as=script; nopush","Link: </commons-c04d24b289df3efc440d.js>; rel=preload; as=script; nopush","Link: </component---src-pages-using-typescript-tsx-192e6058c709fbfe299f.js>; rel=preload; as=script; nopush","Link: </page-data/app-data.json>; rel=preload; as=fetch; crossorigin; nopush","Link: </page-data/using-typescript/page-data.json>; rel=preload; as=fetch; crossorigin; nopush"],"/ru/404.html":["Link: </webpack-runtime-a3f249b8dd01a6115604.js>; rel=preload; as=script; nopush","Link: </framework-7ed2d1b310e30335962d.js>; rel=preload; as=script; nopush","Link: </app-8df6d1293e42d5f129f4.js>; rel=preload; as=script; nopush","Link: </commons-c04d24b289df3efc440d.js>; rel=preload; as=script; nopush","Link: </component---src-pages-404-js-99f86495afad940a713e.js>; rel=preload; as=script; nopush","Link: </page-data/app-data.json>; rel=preload; as=fetch; crossorigin; nopush","Link: </page-data/ru/404.html/page-data.json>; rel=preload; as=fetch; crossorigin; nopush"],"/en/404.html":["Link: </webpack-runtime-a3f249b8dd01a6115604.js>; rel=preload; as=script; nopush","Link: </framework-7ed2d1b310e30335962d.js>; rel=preload; as=script; nopush","Link: </app-8df6d1293e42d5f129f4.js>; rel=preload; as=script; nopush","Link: </commons-c04d24b289df3efc440d.js>; rel=preload; as=script; nopush","Link: </component---src-pages-404-js-99f86495afad940a713e.js>; rel=preload; as=script; nopush","Link: </page-data/app-data.json>; rel=preload; as=fetch; crossorigin; nopush","Link: </page-data/en/404.html/page-data.json>; rel=preload; as=fetch; crossorigin; nopush"]}